[
  {
    "emocion": "enojado",
    "fecha": "2025-06-11T02:31:49.578Z"
  },
  {
    "emocion": "enojado",
    "fecha": "2025-06-11T02:31:59.735Z"
  },
  {
    "emocion": "enojado",
    "fecha": "2025-06-11T02:32:09.438Z"
  },
  {
    "emocion": "enojado",
    "fecha": "2025-06-11T02:32:19.941Z"
  },
  {
    "emocion": "enojado",
    "fecha": "2025-06-11T02:32:29.439Z"
  },
  {
    "emocion": "neutral",
    "fecha": "2025-06-11T02:33:31.365Z"
  },
  {
    "emocion": "triste",
    "fecha": "2025-06-11T02:35:53.462Z"
  },
  {
    "emocion": "neutral",
    "fecha": "2025-06-11T02:36:03.040Z"
  },
  {
    "emocion": "neutral",
    "fecha": "2025-06-11T02:36:13.239Z"
  },
  {
    "emocion": "neutral",
    "fecha": "2025-06-11T06:31:43.614Z"
  },
  {
    "emocion": "neutral",
    "fecha": "2025-06-11T06:31:53.577Z"
  },
  {
    "emocion": "neutral",
    "fecha": "2025-06-11T06:32:03.072Z"
  },
  {
    "emocion": "neutral",
    "fecha": "2025-06-11T06:32:13.580Z"
  },
  {
    "emocion": "neutral",
    "fecha": "2025-06-11T06:32:23.593Z"
  },
  {
    "emocion": "neutral",
    "fecha": "2025-06-11T06:32:33.678Z"
  },
  {
    "emocion": "neutral",
    "fecha": "2025-06-11T06:32:57.900Z"
  },
  {
    "emocion": "neutral",
    "fecha": "2025-06-11T06:33:07.277Z"
  },
  {
    "emocion": "neutral",
    "fecha": "2025-06-11T06:33:17.472Z"
  },
  {
    "emocion": "triste",
    "fecha": "2025-06-11T06:33:27.278Z"
  },
  {
    "emocion": "neutral",
    "fecha": "2025-06-11T06:33:37.378Z"
  },
  {
    "emocion": "enojado",
    "fecha": "2025-06-12T00:54:47.240Z"
  },
  {
    "emocion": "neutral",
    "fecha": "2025-06-12T00:54:57.126Z"
  },
  {
    "emocion": "triste",
    "fecha": "2025-06-12T00:55:06.963Z"
  },
  {
    "emocion": "enojado",
    "fecha": "2025-06-12T00:55:17.121Z"
  },
  {
    "emocion": "enojado",
    "fecha": "2025-06-12T00:55:27.536Z"
  },
  {
    "emocion": "enojado",
    "fecha": "2025-06-12T00:55:37.035Z"
  },
  {
    "emocion": "enojado",
    "fecha": "2025-06-12T00:55:47.632Z"
  },
  {
    "emocion": "enojado",
    "fecha": "2025-06-12T00:55:58.135Z"
  },
  {
    "emocion": "enojado",
    "fecha": "2025-06-12T00:56:07.635Z"
  },
  {
    "emocion": "neutral",
    "fecha": "2025-06-12T00:56:42.940Z"
  },
  {
    "emocion": "enojado",
    "fecha": "2025-06-12T00:57:27.351Z"
  },
  {
    "emocion": "triste",
    "fecha": "2025-06-12T00:58:10.445Z"
  },
  {
    "emocion": "neutral",
    "fecha": "2025-06-12T00:58:38.944Z"
  },
  {
    "emocion": "triste",
    "fecha": "2025-06-12T00:58:49.260Z"
  },
  {
    "emocion": "triste",
    "fecha": "2025-06-12T00:59:22.340Z"
  },
  {
    "emocion": "triste",
    "fecha": "2025-06-12T01:00:28.814Z"
  },
  {
    "emocion": "triste",
    "fecha": "2025-06-12T01:01:04.949Z"
  },
  {
    "emocion": "enojado",
    "fecha": "2025-06-12T01:01:33.146Z"
  },
  {
    "emocion": "enojado",
    "fecha": "2025-06-12T01:02:00.444Z"
  },
  {
    "emocion": "enojado",
    "fecha": "2025-06-12T01:02:45.961Z"
  },
  {
    "emocion": "enojado",
    "fecha": "2025-06-12T01:02:55.234Z"
  },
  {
    "emocion": "agusto",
    "fecha": "2025-06-12T01:03:42.042Z"
  },
  {
    "emocion": "agusto",
    "fecha": "2025-06-12T01:03:42.042Z"
  },
  {
    "emocion": "agusto",
    "fecha": "2025-06-12T01:03:42.042Z"
  },
  {
    "emocion": "agusto",
    "fecha": "2025-06-12T01:03:42.042Z"
  }
]